gpugrap/__init__.py
gpugrap/get_idle.py
gpugrap/gpuinfo.py
gpugrap-0.1.0.dist-info/METADATA
gpugrap-0.1.0.dist-info/WHEEL
gpugrap-0.1.0.dist-info/top_level.txt
gpugrap-0.1.0.dist-info/RECORD
