Metadata-Version: 2.1
Name: gpugrap
Version: 0.1.0
Summary: get idle gpu deivce.
Home-page: https://github.com/seilna/gpugrap
Author: seil.na
Author-email: seil.na@vision.snu.ac.kr
License: UNKNOWN
Download-URL: https://github.com/seilna/gpugrap/archive/master.zip
Keywords: gpu
Platform: UNKNOWN
Requires-Python: >=3
Requires-Dist: pynvml
